[
    {
        "id": 1054867,
        "title": "One Battle After Another",
        "overview": "Washed-up revolutionary Bob exists in a state of stoned paranoia, surviving off-grid with his spirited, self-reliant daughter, Willa. When his evil nemesis resurfaces after 16 years and she goes missing, the former radical scrambles to find her, father and daughter both battling the consequences of his past.",
        "posterPath": "/lbBWwxBht4JFP5PsuJ5onpMqugW.jpg",
        "backdropPath": "/zpEWFNqoN8Qg1SzMMHmaGyOBTdW.jpg",
        "voteAverage": 7.4,
        "releaseDate": "2025-09-23",
        "genreIds": [
            53,
            80,
            35
        ],
        "popularity": 59.2368
    },
    {
        "id": 1078605,
        "title": "Weapons",
        "overview": "When all but one child from the same class mysteriously vanish on the same night at exactly the same time, a community is left questioning who or what is behind their disappearance.",
        "posterPath": "/cpf7vsRZ0MYRQcnLWteD5jK9ymT.jpg",
        "backdropPath": "/8VyTWJrNEyV2MTWvniDVp0MpOAe.jpg",
        "voteAverage": 7.259,
        "releaseDate": "2025-08-04",
        "genreIds": [
            27,
            9648
        ],
        "popularity": 21.5915
    },
    {
        "id": 1062722,
        "title": "Frankenstein",
        "overview": "Dr. Victor Frankenstein, a brilliant but egotistical scientist, brings a creature to life in a monstrous experiment that ultimately leads to the undoing of both the creator and his tragic creation.",
        "posterPath": "/g4JtvGlQO7DByTI6frUobqvSL3R.jpg",
        "backdropPath": "/hpXBJxLD2SEf8l2CspmSeiHrBKX.jpg",
        "voteAverage": 7.7,
        "releaseDate": "2025-10-17",
        "genreIds": [
            18,
            14,
            27
        ],
        "popularity": 33.1275
    },
    {
        "id": 911430,
        "title": "F1",
        "overview": "Racing legend Sonny Hayes is coaxed out of retirement to lead a struggling Formula 1 team—and mentor a young hotshot driver—while chasing one more chance at glory.",
        "posterPath": "/vqBmyAj0Xm9LnS1xe1MSlMAJyHq.jpg",
        "backdropPath": "/rZWkXnIyTLzUJpHSUpOb7vgB0BL.jpg",
        "voteAverage": 7.75,
        "releaseDate": "2025-06-25",
        "genreIds": [
            28,
            18
        ],
        "popularity": 31.1107
    },
    {
        "id": 1233413,
        "title": "Sinners",
        "overview": "Trying to leave their troubled lives behind, twin brothers return to their hometown to start again, only to discover that an even greater evil is waiting to welcome them back.",
        "posterPath": "/705nQHqe4JGdEisrQmVYmXyjs1U.jpg",
        "backdropPath": "/nAxGnGHOsfzufThz20zgmRwKur3.jpg",
        "voteAverage": 7.5,
        "releaseDate": "2025-04-16",
        "genreIds": [
            27,
            28,
            53
        ],
        "popularity": 58.4317
    },
    {
        "id": 83533,
        "title": "Avatar: Fire and Ash",
        "overview": "In the wake of the devastating war against the RDA and the loss of their eldest son, Jake Sully and Neytiri face a new threat on Pandora: the Ash People, a violent and power-hungry Na'vi tribe led by the ruthless Varang. Jake's family must fight for their survival and the future of Pandora in a conflict that pushes them to their emotional and physical limits.",
        "posterPath": "/bRBeSHfGHwkEpImlhxPmOcUsaeg.jpg",
        "backdropPath": "/sdZSjtGUTSN8B3al5o0f2WoQfQQ.jpg",
        "voteAverage": 7.26,
        "releaseDate": "2025-12-17",
        "genreIds": [
            878,
            12,
            14
        ],
        "popularity": 304.572
    },
    {
        "id": 858024,
        "title": "Hamnet",
        "overview": "The powerful story of love and loss that inspired the creation of Shakespeare's timeless masterpiece, Hamlet.",
        "posterPath": "/vbeyOZm2bvBXcbgPD3v6o94epPX.jpg",
        "backdropPath": "/73BClq9FOcrWrutnpiqhCNEWEwJ.jpg",
        "voteAverage": 7.714,
        "releaseDate": "2025-11-26",
        "genreIds": [
            18,
            10749,
            36
        ],
        "popularity": 30.5602
    },
    {
        "id": 1124566,
        "title": "Sentimental Value",
        "overview": "Sisters Nora and Agnes reunite with their estranged father, the charismatic Gustav, a once-renowned director who offers stage actress Nora a role in what he hopes will be his comeback film. When Nora turns it down, she soon discovers he has given her part to an eager young Hollywood star.",
        "posterPath": "/pz9NCWxxOk3o0W3v1Zkhawrwb4i.jpg",
        "backdropPath": "/oLgtpxK4aGZ7S8aiE3rDwahqkL2.jpg",
        "voteAverage": 7.5,
        "releaseDate": "2025-08-20",
        "genreIds": [
            18
        ],
        "popularity": 14.538
    },
    {
        "id": 1393151,
        "title": "Mr. Nobody Against Putin",
        "overview": "As Russia launches its full-scale invasion of Ukraine, primary schools across Russia’s hinterlands are transformed into recruitment stages for the war. Facing the ethical dilemma of working in a system defined by propaganda and violence, a brave teacher goes undercover to film what’s really happening in his own school.",
        "posterPath": "/ss4NEGmPxgm4D73iMFeyjbE1m9b.jpg",
        "backdropPath": "/3A0dDfZq5WxdDGt8qzmhFXqVZxJ.jpg",
        "voteAverage": 7.528,
        "releaseDate": "2025-06-06",
        "genreIds": [
            99
        ],
        "popularity": 6.12
    },
    {
        "id": 803796,
        "title": "KPop Demon Hunters",
        "overview": "When K-pop superstars Rumi, Mira and Zoey aren't selling out stadiums, they're using their secret powers to protect their fans from supernatural threats.",
        "posterPath": "/zT7Lhw3BhJbMkRqm9Zlx2YGMsY0.jpg",
        "backdropPath": "/w3Bi0wygeFQctn6AqFTwhGNXRwL.jpg",
        "voteAverage": 8.034,
        "releaseDate": "2025-06-20",
        "genreIds": [
            14,
            10402,
            35,
            16
        ],
        "popularity": 43.7644
    },
    {
        "id": 1442908,
        "title": "The Singers",
        "overview": "An impromptu singing contest at a dive bar turns a lonely night into a soul-baring moment of shared harmony.",
        "posterPath": "/a6wheh1243vceZ7Dqb0knYmKqaj.jpg",
        "backdropPath": "/oTWgvLnMjjsVNdVTZjf5CEnihhw.jpg",
        "voteAverage": 6.605,
        "releaseDate": "2026-02-17",
        "genreIds": [
            10402,
            18,
            35
        ],
        "popularity": 4.5041
    },
    {
        "id": 1525091,
        "title": "All the Empty Rooms",
        "overview": "A journalist and a photographer set out to memorialize the bedrooms left behind by children killed in school shootings.",
        "posterPath": "/A2sXJBlf3QmzOlpx8J4qIxbq0W5.jpg",
        "backdropPath": "/jmr5GZmQ2Ds3REQi4FJ4GA0vUBJ.jpg",
        "voteAverage": 7.319,
        "releaseDate": "2025-08-31",
        "genreIds": [
            99
        ],
        "popularity": 2.4924
    },
    {
        "id": 1142149,
        "title": "The Girl Who Cried Pearls",
        "overview": "A poor boy’s love for a girl whose tears turn to pearls leads him into a perilous bargain between love, greed, and survival.",
        "posterPath": "/sqdqvstmM2vOBnb5beVT8lOQ4Oi.jpg",
        "backdropPath": "/rjoLKgOZeqdWUMEYhVq2Vf7JVxu.jpg",
        "voteAverage": 7.517,
        "releaseDate": "2025-06-08",
        "genreIds": [
            16,
            18,
            14
        ],
        "popularity": 1.6274
    },
    {
        "id": 1340625,
        "title": "Two People Exchanging Saliva",
        "overview": "In a society where kissing is punishable by death, and people pay for things by receiving slaps to the face, Angine, an unhappy woman, shops compulsively in a department store. There, she becomes fascinated by a playful salesgirl. Despite the prohibition of kissing, the two become close, raising the suspicions of a jealous colleague.",
        "posterPath": "/hZZbpGiQsPR4X4czS9Iu8JGNHYU.jpg",
        "backdropPath": "/zKpouA46GDQc8nY7FsBkJBh1EnB.jpg",
        "voteAverage": 7.591,
        "releaseDate": "2025-11-27",
        "genreIds": [
            18,
            14,
            878
        ],
        "popularity": 1.9842
    }
]