[
    {
        "id": 59967,
        "title": "Looper",
        "overview": "In the year 2044, time travel has not yet been invented but in 30 years it will have been. When the mob wants to get rid of someone, they will send their target into the past where a looper, a hired gun, like Joe is waiting to mop up. Joe is getting rich and life is good until the day the mob decides to close the loop, sending back Joe's future self for assassination.",
        "posterPath": "/sNjL6SqErDBE8OUZlrDLkexfsCj.jpg",
        "backdropPath": "/4GPCnwvTbsDleH5QIOyDLMsK8a2.jpg",
        "voteAverage": 6.904,
        "releaseDate": "2012-09-26",
        "genreIds": [
            28,
            53,
            878
        ],
        "popularity": 6.4317
    },
    {
        "id": 105,
        "title": "Back to the Future",
        "overview": "Eighties teenager Marty McFly is accidentally sent back in time to 1955, inadvertently disrupting his parents' first meeting and attracting his mother's romantic interest. Marty must repair the damage to history by rekindling his parents' romance and - with the help of his eccentric inventor friend Doc Brown - return to 1985.",
        "posterPath": "/vN5B5WgYscRGcQpVhHl6p9DDTP0.jpg",
        "backdropPath": "/qskzmLTbarKnXDbo2HRj4NJ3vcW.jpg",
        "voteAverage": 8.325,
        "releaseDate": "1985-07-03",
        "genreIds": [
            12,
            35,
            878
        ],
        "popularity": 20.5223
    },
    {
        "id": 22494,
        "title": "Frequently Asked Questions About Time Travel",
        "overview": "Follows three social outcasts -- two geeks and a cynic -- as they attempt to navigate a time-travel conundrum in the middle of a British pub.",
        "posterPath": "/r67KzlHkdiwe3fBWzImEkNOg1Y.jpg",
        "backdropPath": "/hw3XpVWJ0XJlnevjpDHIHO2bY7p.jpg",
        "voteAverage": 6.9,
        "releaseDate": "2009-04-24",
        "genreIds": [
            35,
            18,
            10749,
            878
        ],
        "popularity": 1.4516
    },
    {
        "id": 165,
        "title": "Back to the Future Part II",
        "overview": "Marty and Doc are at it again as the time-traveling duo head to 2015 to nip some McFly family woes in the bud. But things go awry thanks to bully Biff Tannen and a pesky sports almanac. In a last-ditch attempt to set things straight, Marty finds himself bound for 1955 and face to face with his teenage parents -- again.",
        "posterPath": "/hQq8xZe5uLjFzSBt4LanNP7SQjl.jpg",
        "backdropPath": "/w6tPctxWAsHoQXeKxxNOT6lYKpx.jpg",
        "voteAverage": 7.777,
        "releaseDate": "1989-11-22",
        "genreIds": [
            12,
            35,
            878
        ],
        "popularity": 10.2058
    },
    {
        "id": 196,
        "title": "Back to the Future Part III",
        "overview": "The final installment finds Marty digging the trusty DeLorean out of a mineshaft and looking for Doc in the Wild West of 1885. But when their time machine breaks down, the travelers are stranded in a land of spurs. More problems arise when Doc falls for pretty schoolteacher Clara Clayton, and Marty tangles with Buford Tannen.",
        "posterPath": "/crzoVQnMzIrRfHtQw0tLBirNfVg.jpg",
        "backdropPath": "/AtF7TESJEMmImBRUj9Z7HmW2ZH0.jpg",
        "voteAverage": 7.49,
        "releaseDate": "1990-05-25",
        "genreIds": [
            12,
            35,
            878
        ],
        "popularity": 6.4835
    },
    {
        "id": 137,
        "title": "Groundhog Day",
        "overview": "A cynical TV weatherman, along with his idealistic producer and his sardonic cameraman, is sent to report on Groundhog Day in the small town of Punxsutawney, where he finds himself repeating the same day over and over.",
        "posterPath": "/gCgt1WARPZaXnq523ySQEUKinCs.jpg",
        "backdropPath": "/ttBydD0SynC0TMkW3AcnmsySkLp.jpg",
        "voteAverage": 7.626,
        "releaseDate": "1993-02-11",
        "genreIds": [
            10749,
            14,
            35
        ],
        "popularity": 9.7323
    },
    {
        "id": 460024,
        "title": "Stasis",
        "overview": "After a night out of partying and left behind by her friends, Ava wakes up and sneaks back home only to find that she's already safe in bed. But that's not Ava - it's someone who looks just like her. A time-traveling fugitive has stolen Ava's body, her identity, and her life. What's more -- she's not alone. There are others, hiding in the past, secretly living among us, plotting to alter the future. Without her body, Ava is a virtual ghost, silent and invisible to the world. And, so far as she knows, she's the only one who can stop them and put the timeline back on course.",
        "posterPath": "/g0AgiPF1qBObVDLK7pwncujVpuo.jpg",
        "backdropPath": "/r8iAdcutxYp8tnSWa69QlxD0cZ0.jpg",
        "voteAverage": 3.6,
        "releaseDate": "2017-06-02",
        "genreIds": [
            12,
            878
        ],
        "popularity": 0.5507
    },
    {
        "id": 15691,
        "title": "Doctor Who",
        "overview": "The Seventh Doctor becomes the Eighth. And on the streets of San Francisco – alongside new ally Grace Holloway - he battles the Master.",
        "posterPath": "/cwae2p7JcRNtz1CvNCzpX5ad96V.jpg",
        "backdropPath": "/26MVKVGQf1J0yrzJx97Ww4DLslV.jpg",
        "voteAverage": 6.2,
        "releaseDate": "1996-05-12",
        "genreIds": [
            10770,
            12,
            878
        ],
        "popularity": 8.4676
    },
    {
        "id": 63,
        "title": "Twelve Monkeys",
        "overview": "In the year 2035, convict James Cole reluctantly volunteers to be sent back in time to discover the origin of a deadly virus that wiped out nearly all of the earth's population and forced the survivors into underground communities. But when Cole is mistakenly sent to 1990 instead of 1996, he's arrested and locked up in a mental hospital. There he meets psychiatrist Dr. Kathryn Railly and the son of a famous virus expert who may hold the key to the Army of the 12 Monkeys; thought to be responsible for unleashing the killer disease.",
        "posterPath": "/gt3iyguaCIw8DpQZI1LIN5TohM2.jpg",
        "backdropPath": "/mKIkGoyuR71qz6FdiEiOjxvBQcS.jpg",
        "voteAverage": 7.602,
        "releaseDate": "1995-12-29",
        "genreIds": [
            878,
            53,
            9648
        ],
        "popularity": 9.0411
    },
    {
        "id": 87101,
        "title": "Terminator Genisys",
        "overview": "The year is 2029. John Connor, leader of the resistance continues the war against the machines. At the Los Angeles offensive, John's fears of the unknown future begin to emerge when TECOM spies reveal a new plot by SkyNet that will attack him from both fronts; past and future, and will ultimately change warfare forever.",
        "posterPath": "/oZRVDpNtmHk8M1VYy1aeOWUXgbC.jpg",
        "backdropPath": "/wvlIoof1FnKPLv9jAYanuP31V0C.jpg",
        "voteAverage": 5.949,
        "releaseDate": "2015-06-23",
        "genreIds": [
            878,
            28,
            53
        ],
        "popularity": 14.1463
    },
    {
        "id": 218,
        "title": "The Terminator",
        "overview": "In the post-apocalyptic future, reigning tyrannical supercomputers teleport a cyborg assassin known as the \"Terminator\" back to 1984 to kill Sarah Connor, whose unborn son is destined to lead insurgents against 21st century mechanical hegemony. Meanwhile, the human-resistance movement dispatches a lone warrior to safeguard Sarah. Can he stop the virtually indestructible killing machine?",
        "posterPath": "/qvktm0BHcnmDpul4Hz01GIazWPr.jpg",
        "backdropPath": "/5BZtN173AXqReBJTxE2ZikBDCl7.jpg",
        "voteAverage": 7.677,
        "releaseDate": "1984-10-26",
        "genreIds": [
            28,
            53,
            878
        ],
        "popularity": 17.733
    },
    {
        "id": 280,
        "title": "Terminator 2: Judgment Day",
        "overview": "Ten years after the events of the original, a reprogrammed T-800 is sent back in time to protect young John Connor from the shape-shifting T-1000. Together with his mother Sarah, he fights to stop Skynet from triggering a nuclear apocalypse.",
        "posterPath": "/jFTVD4XoWQTcg7wdyJKa8PEds5q.jpg",
        "backdropPath": "/izkMjmhauFx9DjoBQqM5sM5WAwE.jpg",
        "voteAverage": 8.142,
        "releaseDate": "1991-07-03",
        "genreIds": [
            28,
            53,
            878
        ],
        "popularity": 18.215
    },
    {
        "id": 534,
        "title": "Terminator Salvation",
        "overview": "All grown up in post-apocalyptic 2018, John Connor must lead the resistance of humans against the increasingly dominating militaristic robots. But when Marcus Wright appears, his existence confuses the mission as Connor tries to determine whether Wright has come from the future or the past -- and whether he's friend or foe.",
        "posterPath": "/gw6JhlekZgtKUFlDTezq3j5JEPK.jpg",
        "backdropPath": "/uifaXfJxjTMeNttw5u04nHx1G5w.jpg",
        "voteAverage": 6.082,
        "releaseDate": "2009-05-20",
        "genreIds": [
            28,
            878,
            53
        ],
        "popularity": 8.305
    },
    {
        "id": 296,
        "title": "Terminator 3: Rise of the Machines",
        "overview": "It's been 10 years since John Connor saved Earth from Judgment Day, and he's now living under the radar, steering clear of using anything Skynet can trace. That is, until he encounters T-X, a robotic assassin ordered to finish what T-1000 started. Good thing Connor's former nemesis, the Terminator, is back to aid the now-adult Connor … just like he promised.",
        "posterPath": "/nvsoLAclNfpyJSp73TiGKwZoqJW.jpg",
        "backdropPath": "/kbXMOnz2RhTSAbLtHX5hy5AXtwv.jpg",
        "voteAverage": 6.183,
        "releaseDate": "2003-07-02",
        "genreIds": [
            28,
            53,
            878
        ],
        "popularity": 8.6154
    },
    {
        "id": 49160,
        "title": "The Time Travelers",
        "overview": "Research scientists experimenting with time warps are accidentally propelled forward into an unbearable future.",
        "posterPath": "/cc3deOS6bejonPRPLsbZBg1LlPN.jpg",
        "backdropPath": "/qpGMck9EPT1nzDNWPAwpCKJQiqq.jpg",
        "voteAverage": 5.1,
        "releaseDate": "1964-10-29",
        "genreIds": [
            878,
            12,
            18
        ],
        "popularity": 0.7185
    },
    {
        "id": 1649,
        "title": "Bill & Ted's Bogus Journey",
        "overview": "Amiable slackers Bill and Ted are once again roped into a fantastical adventure when De Nomolos, a villain from the future, sends evil robot duplicates of the two lads to terminate and replace them. The robot doubles actually succeed in killing Bill and Ted, but the two are determined to escape the afterlife, challenging the Grim Reaper to a series of games in order to return to the land of the living.",
        "posterPath": "/tldtDfLnPFOtTWp758EmIP2Hbz5.jpg",
        "backdropPath": "/4PMSgLOzPFgyzARQBhhX4vS9oOW.jpg",
        "voteAverage": 6.3,
        "releaseDate": "1991-07-19",
        "genreIds": [
            12,
            35,
            878
        ],
        "popularity": 2.4345
    },
    {
        "id": 673,
        "title": "Harry Potter and the Prisoner of Azkaban",
        "overview": "Year three at Hogwarts means new fun and challenges as Harry learns the delicate art of approaching a Hippogriff, transforming shape-shifting Boggarts into hilarity and even turning back time. But the term also brings danger: soul-sucking Dementors hover over the school, an ally of the accursed He-Who-Cannot-Be-Named lurks within the castle walls, and fearsome wizard Sirius Black escapes Azkaban. And Harry will confront them all.",
        "posterPath": "/aWxwnYoe8p2d2fcxOqtvAtJ72Rw.jpg",
        "backdropPath": "/vbk5CfaAHOjQPSAcYm6AoRRz2Af.jpg",
        "voteAverage": 8.008,
        "releaseDate": "2004-05-31",
        "genreIds": [
            12,
            14
        ],
        "popularity": 18.6942
    },
    {
        "id": 1648,
        "title": "Bill & Ted's Excellent Adventure",
        "overview": "Bill and Ted are high school buddies starting a band. They are also about to fail their history class—which means Ted would be sent to military school—but receive help from Rufus, a traveller from a future where their band is the foundation for a perfect society. With the use of Rufus' time machine, Bill and Ted travel to various points in history, returning with important figures to help them complete their final history presentation.",
        "posterPath": "/tV25lGWGWGEqUe3U0xjQTBgilSx.jpg",
        "backdropPath": "/94CCJ95vRXZocycBbuvxIwM3CCP.jpg",
        "voteAverage": 6.851,
        "releaseDate": "1989-02-17",
        "genreIds": [
            12,
            35,
            878
        ],
        "popularity": 11.515
    },
    {
        "id": 376292,
        "title": "Paradox",
        "overview": "A group of scientists are experimenting with time travel, and they manage to send one of their group ahead in time one hour. But when he comes back, he tells them that they’ll all be dead within the next hour unless they shut the machine down.",
        "posterPath": "/nkjDIxzRwFMDvANnpdEIcT4whQe.jpg",
        "backdropPath": "/2CHRCwkr5yoA9xdihzHrXL3eNre.jpg",
        "voteAverage": 4.6,
        "releaseDate": "2016-04-22",
        "genreIds": [
            28,
            878
        ],
        "popularity": 0.8919
    },
    {
        "id": 347945,
        "title": "Synchronicity",
        "overview": "A daring physicist travels into the past to stop a mysterious woman from stealing his invention. But once there, he uncovers a surprising truth about the machine, the woman, and his own fractured reality.",
        "posterPath": "/wGHoYDswvx96PVF43qFErVAnQHS.jpg",
        "backdropPath": "/d3dDgrzE5DDR5vDe4qNbXmN57ey.jpg",
        "voteAverage": 5.7,
        "releaseDate": "2015-07-22",
        "genreIds": [
            9648,
            878,
            53
        ],
        "popularity": 1.2917
    },
    {
        "id": 410199,
        "title": "ARQ",
        "overview": "Two old friends living in a dystopic future become trapped in a mysterious time loop — one that may have something to do with an ongoing battle between an omnipotent corporation and a ragtag band of rebels.",
        "posterPath": "/mU4VeXVK18JtCZsy7i0zczlA9p7.jpg",
        "backdropPath": "/oX6rYilUqQJMcMzCn6K61UifOnN.jpg",
        "voteAverage": 6.114,
        "releaseDate": "2016-09-16",
        "genreIds": [
            878,
            53
        ],
        "popularity": 3.7357
    },
    {
        "id": 227719,
        "title": "Project Almanac",
        "overview": "A group of teens discover secret plans of a time machine, and construct one. However, things start to get out of control.",
        "posterPath": "/9u5Rb0e7mx8qOO7zj39KnIRWClr.jpg",
        "backdropPath": "/eyJk5LTMLIeAN2kVsP0yXrPZJfl.jpg",
        "voteAverage": 6.781,
        "releaseDate": "2015-01-28",
        "genreIds": [
            878,
            53
        ],
        "popularity": 3.3698
    },
    {
        "id": 284052,
        "title": "Doctor Strange",
        "overview": "After his career is destroyed, a brilliant but arrogant surgeon gets a new lease on life when a sorcerer takes him under her wing and trains him to defend the world against evil.",
        "posterPath": "/xf8PbyQcR5ucXErmZNzdKR0s8ya.jpg",
        "backdropPath": "/3zvZ699gMW2RhWc0GisIukzq0Ls.jpg",
        "voteAverage": 7.418,
        "releaseDate": "2016-10-25",
        "genreIds": [
            14,
            12,
            28
        ],
        "popularity": 14.474
    },
    {
        "id": 127585,
        "title": "X-Men: Days of Future Past",
        "overview": "The ultimate X-Men ensemble fights a war for the survival of the species across two time periods as they join forces with their younger selves in an epic battle that must change the past – to save our future.",
        "posterPath": "/tYfijzolzgoMOtegh1Y7j2Enorg.jpg",
        "backdropPath": "/fctQU5MoXgJ5pNMljFzlEFXwfSu.jpg",
        "voteAverage": 7.53,
        "releaseDate": "2014-05-15",
        "genreIds": [
            28,
            12,
            878
        ],
        "popularity": 10.8417
    },
    {
        "id": 293970,
        "title": "The Final Girls",
        "overview": "A young woman grieving the loss of her mother, a famous scream queen from the 1980s, finds herself pulled into the world of her mom's most famous movie. Reunited, the women must fight off the film's maniacal killer.",
        "posterPath": "/gQYKSRVo5iZACFOY6x50RblI6rx.jpg",
        "backdropPath": "/vLRu9nLJ14HtVq9PrYCTr0Emb39.jpg",
        "voteAverage": 6.385,
        "releaseDate": "2015-10-09",
        "genreIds": [
            35,
            27
        ],
        "popularity": 1.9788
    },
    {
        "id": 13475,
        "title": "Star Trek",
        "overview": "The fate of the galaxy rests in the hands of bitter rivals. One, James Kirk, is a delinquent, thrill-seeking Iowa farm boy. The other, Spock, a Vulcan, was raised in a logic-based society that rejects all emotion. As fiery instinct clashes with calm reason, their unlikely but powerful partnership is the only thing capable of leading their crew through unimaginable danger, boldly going where no one has gone before. The human adventure has begun again.",
        "posterPath": "/hN2ZtF3Uw6mhIHZiqL0SKzELtKn.jpg",
        "backdropPath": "/cqXEwYFcwyKPZCKl1jAPaG3cMsl.jpg",
        "voteAverage": 7.429,
        "releaseDate": "2009-05-06",
        "genreIds": [
            878,
            28,
            12
        ],
        "popularity": 8.8863
    },
    {
        "id": 168,
        "title": "Star Trek IV: The Voyage Home",
        "overview": "When a huge alien probe enters the galaxy and begins to vaporize Earth's oceans, Kirk and his crew must travel back in time in order to bring back whales and save the planet.",
        "posterPath": "/xY5TzGXJOB3L9rhZ1MbbPyVlW5J.jpg",
        "backdropPath": "/2LiU13aDAWpU2mX25JdacTzBnyr.jpg",
        "voteAverage": 7.17,
        "releaseDate": "1986-11-26",
        "genreIds": [
            878,
            12
        ],
        "popularity": 4.1071
    },
    {
        "id": 137113,
        "title": "Edge of Tomorrow",
        "overview": "Major Bill Cage is an officer who has never seen a day of combat when he is unceremoniously demoted and dropped into combat. Cage is killed within minutes, managing to take an alpha alien down with him. He awakens back at the beginning of the same day and is forced to fight and die again... and again - as physical contact with the alien has thrown him into a time loop.",
        "posterPath": "/nBM9MMa2WCwvMG4IJ3eiGUdbPe6.jpg",
        "backdropPath": "/4V1yIoAKPMRQwGBaSses8Bp2nsi.jpg",
        "voteAverage": 7.635,
        "releaseDate": "2014-05-27",
        "genreIds": [
            28,
            878
        ],
        "popularity": 9.7046
    },
    {
        "id": 397837,
        "title": "Before I Fall",
        "overview": "Samantha Kingston has everything. Then, everything changes. After one fateful night, she wakes up with no future at all. Trapped into reliving the same day over and over, she begins to question just how perfect her life really was.",
        "posterPath": "/eowzonDJMCuNXoJGVkP9Z7oCmiM.jpg",
        "backdropPath": "/q0X5l5GfbqxKuof0XHEIuh94RKb.jpg",
        "voteAverage": 6.963,
        "releaseDate": "2017-03-02",
        "genreIds": [
            18,
            14
        ],
        "popularity": 2.3723
    },
    {
        "id": 141,
        "title": "Donnie Darko",
        "overview": "After narrowly escaping a bizarre accident, a troubled teenager is plagued by visions of a large bunny rabbit that manipulates him to commit a series of crimes.",
        "posterPath": "/fhQoQfejY1hUcwyuLgpBrYs6uFt.jpg",
        "backdropPath": "/msCHK5Kh1YbdZ0zPJ2nzPUhhSN9.jpg",
        "voteAverage": 7.764,
        "releaseDate": "2001-01-19",
        "genreIds": [
            14,
            18,
            9648
        ],
        "popularity": 10.6481
    },
    {
        "id": 766,
        "title": "Army of Darkness",
        "overview": "Ash, a handsome, shotgun-toting, chainsaw-armed department store clerk, is time warped backwards into England's Dark Ages, where he romances a beauty and faces legions of the undead.",
        "posterPath": "/xsgTuAtR2zSH8Umg3jWZcZjlDpe.jpg",
        "backdropPath": "/5RPXs9g0sZ9Woo4pNLxdXdge7tc.jpg",
        "voteAverage": 7.261,
        "releaseDate": "1992-10-31",
        "genreIds": [
            14,
            27,
            35
        ],
        "popularity": 5.0422
    },
    {
        "id": 8831,
        "title": "Timecop",
        "overview": "In 2004, an officer for a security agency that regulates time travel must fend for his life against a shady politician who has a tie to his past.",
        "posterPath": "/bgxP6ws8ErBiarnb4S93vv0lkf4.jpg",
        "backdropPath": "/iNfDwioDBzqodomLbMfV8ZXj0yL.jpg",
        "voteAverage": 6.005,
        "releaseDate": "1994-09-15",
        "genreIds": [
            53,
            878,
            28,
            80
        ],
        "popularity": 3.4621
    },
    {
        "id": 157336,
        "title": "Interstellar",
        "overview": "The adventures of a group of explorers who make use of a newly discovered wormhole to surpass the limitations on human space travel and conquer the vast distances involved in an interstellar voyage.",
        "posterPath": "/yQvGrMoipbRoddT0ZR8tPoR7NfX.jpg",
        "backdropPath": "/2ssWTSVklAEc98frZUQhgtGHx7s.jpg",
        "voteAverage": 8.469,
        "releaseDate": "2014-11-05",
        "genreIds": [
            12,
            18,
            878
        ],
        "popularity": 48.8409
    },
    {
        "id": 433251,
        "title": "Naked",
        "overview": "Following a wild night out with his best man, Rob Anderson wakes up to find himself naked in an elevator on the morning of his wedding day and is forced to relive the morning over and over again.",
        "posterPath": "/qXRmYSB9C6SHdxTgY3wB72Riz9Y.jpg",
        "backdropPath": "/p1jxdxtZA8SdmgGgfYepfUhQ3NG.jpg",
        "voteAverage": 5.8,
        "releaseDate": "2017-08-11",
        "genreIds": [
            35
        ],
        "popularity": 3.0464
    },
    {
        "id": 30647,
        "title": "12:01 PM",
        "overview": "12:01 PM is a 1990 short film directed by Jonathan Heap and starring Kurtwood Smith. It follows Myron Castleman, an everyman who keeps repeating the same hour of his life, from 12:01 PM to 1:00 PM. The film was nominated for an Oscar for Best Live Action Short Film.",
        "posterPath": "/zT5R8VahhZlE1TDcwEtmvyr8c8K.jpg",
        "backdropPath": null,
        "voteAverage": 6.9,
        "releaseDate": "1990-01-01",
        "genreIds": [
            878
        ],
        "popularity": 0.4539
    },
    {
        "id": 17803,
        "title": "12:01",
        "overview": "Office employee Barry Thomas is caught in a \"time bounce\" caused by a glitch in the company's secret project. Now the same day occurs again and again - and Barry's the only one who can do anything about it, including saving the life of beautiful research assistant Lisa Fredericks.",
        "posterPath": "/xK3d7mT6D7v2y8jp5Kv7c9FXzen.jpg",
        "backdropPath": "/jZBJfWHHGw9kbRQs2hnY1n1bQpm.jpg",
        "voteAverage": 6.2,
        "releaseDate": "1993-07-05",
        "genreIds": [
            878,
            53,
            10770
        ],
        "popularity": 1.4284
    },
    {
        "id": 2134,
        "title": "The Time Machine",
        "overview": "A Victorian Englishman travels to the far future and finds that humanity has divided into two hostile species.",
        "posterPath": "/sotBnRlFJ67cPisjAUXzbPxi9kC.jpg",
        "backdropPath": "/bUA6Fu0C2jGqrjn0A9AJwTRpq41.jpg",
        "voteAverage": 7.344,
        "releaseDate": "1960-05-25",
        "genreIds": [
            53,
            12,
            14,
            878,
            10749
        ],
        "popularity": 2.721
    },
    {
        "id": 273271,
        "title": "Time Lapse",
        "overview": "Three friends discover a mysterious machine that takes pictures 24 hours into the future and conspire to use it for personal gain, until disturbing and dangerous images begin to develop.",
        "posterPath": "/lfggWOEZ9pL34XKYisBTJ0vFnFS.jpg",
        "backdropPath": "/dmiyWvFdoId9CJ0fCLQRKruRkBt.jpg",
        "voteAverage": 6.5,
        "releaseDate": "2014-05-24",
        "genreIds": [
            53,
            878,
            9648
        ],
        "popularity": 1.7543
    },
    {
        "id": 36819,
        "title": "Time Bandits",
        "overview": "Young history buff Kevin can scarcely believe it when six dwarfs emerge from his closet one night. Former employees of the Supreme Being, they've purloined a map charting all of the holes in the fabric of time and are using it to steal treasures from different historical eras. Taking Kevin with them, they variously drop in on Napoleon, Robin Hood and King Agamemnon before the Supreme Being catches up with them.",
        "posterPath": "/4VZtpwdhHQSa4LUkvujyGAHb1hG.jpg",
        "backdropPath": "/qKERrt3UU1ml8Q9zdsLPpoQ5r3.jpg",
        "voteAverage": 6.627,
        "releaseDate": "1981-07-13",
        "genreIds": [
            10751,
            14,
            878,
            12,
            35
        ],
        "popularity": 3.0535
    },
    {
        "id": 243938,
        "title": "Hot Tub Time Machine 2",
        "overview": "After their first adventure with the Hot Tub Time Machine, Lou and Nick are living very well off their ill-gotten gains, while Jacob still cannot rely on Lou to be a positive role model. When an unknown assailant breaks into Lou's mansion and shoots him, Nick and Jacob take him for another trip in the hot tub. They emerge in the year 2025, where they must figure out who shot Lou and prevent it from happening again.",
        "posterPath": "/lBroHetSm8RMI8zp7ThpFJsw9E1.jpg",
        "backdropPath": "/iz0gx0msnS2G2vUcmigSE7aN4CL.jpg",
        "voteAverage": 5.2,
        "releaseDate": "2015-02-20",
        "genreIds": [
            35
        ],
        "popularity": 1.6198
    },
    {
        "id": 23048,
        "title": "Hot Tub Time Machine",
        "overview": "Four pals are stuck in a rut in adulthood: Adam has just been dumped, Lou is a hopeless party animal, Nick is a henpecked husband, and Jacob does nothing but play video games in his basement. But they get a chance to brighten their future by changing their past after a night of heavy drinking in a ski-resort hot tub results in their waking up in 1986.",
        "posterPath": "/wjzbVXAes1acbh6k4OO5xVfy5.jpg",
        "backdropPath": "/wwzuxanisjA7GhZOPYaWlfmlCKY.jpg",
        "voteAverage": 6.043,
        "releaseDate": "2010-03-26",
        "genreIds": [
            878,
            35,
            12
        ],
        "popularity": 4.9829
    },
    {
        "id": 41154,
        "title": "Men in Black 3",
        "overview": "Agents J and K are back...in time. J has seen some inexplicable things in his 15 years with the Men in Black, but nothing, not even aliens, perplexes him as much as his wry, reticent partner. But when K's life and the fate of the planet are put at stake, Agent J will have to travel back in time to put things right. J discovers that there are secrets to the universe that K never told him - secrets that will reveal themselves as he teams up with the young Agent K to save his partner, the agency, and the future of humankind.",
        "posterPath": "/90DdoEStzeObs96fsYf4GG544iN.jpg",
        "backdropPath": "/5AhpUb8CAP0jZ4Wrn7AsRUYjZxB.jpg",
        "voteAverage": 6.54,
        "releaseDate": "2012-05-23",
        "genreIds": [
            28,
            35,
            878
        ],
        "popularity": 8.5964
    },
    {
        "id": 206487,
        "title": "Predestination",
        "overview": "Predestination chronicles the life of a Temporal Agent sent on an intricate series of time-travel journeys designed to prevent future killers from committing their crimes. Now, on his final assignment, the Agent must stop the one criminal that has eluded him throughout time and prevent a devastating attack in which thousands of lives will be lost.",
        "posterPath": "/38Xr1JnV1ZcLQ55zmdSp6n475cZ.jpg",
        "backdropPath": "/cvq9cRMDJIGzNpHaPVGFftqPcLj.jpg",
        "voteAverage": 7.417,
        "releaseDate": "2014-08-28",
        "genreIds": [
            878,
            53
        ],
        "popularity": 5.4319
    },
    {
        "id": 1954,
        "title": "The Butterfly Effect",
        "overview": "A young man struggles to access sublimated childhood memories. He finds a technique that allows him to travel back into the past, to occupy his childhood body and change history. However, he soon finds that every change he makes has unexpected consequences.",
        "posterPath": "/ea5iv7TWMh18fOKoRGgmtcg85Gx.jpg",
        "backdropPath": "/yriYPLqyFqPW0QXaegT1KmWXk9a.jpg",
        "voteAverage": 7.573,
        "releaseDate": "2004-01-17",
        "genreIds": [
            878,
            53
        ],
        "popularity": 7.7286
    },
    {
        "id": 9278,
        "title": "Freejack",
        "overview": "Time-traveling bounty hunters find a doomed race-car driver in the past and bring him to 2009 New York, where his mind will be replaced with that of a terminally ill billionaire.",
        "posterPath": "/lSN8lIX90Az0t1qvIXC4MlCvd9a.jpg",
        "backdropPath": "/8FlHUvNOSANeo8Y8adBNJanEib.jpg",
        "voteAverage": 5.5,
        "releaseDate": "1992-01-17",
        "genreIds": [
            878,
            28,
            80,
            18
        ],
        "popularity": 3.0418
    },
    {
        "id": 4296,
        "title": "Millennium",
        "overview": "An investigator seeking the cause of an airline disaster discovers the involvement of an organisation of time travellers from a future Earth irreparably polluted who seek to rejuvenate the human race from those about to die in the past. Based on a novel by John Varley.",
        "posterPath": "/mFGCK7RnFnRXR6CweAhQw030Zv7.jpg",
        "backdropPath": "/coikapUWLhdIie0PdmEjf881zmF.jpg",
        "voteAverage": 5.362,
        "releaseDate": "1989-08-25",
        "genreIds": [
            878
        ],
        "popularity": 1.7517
    },
    {
        "id": 1687,
        "title": "Escape from the Planet of the Apes",
        "overview": "The world is shocked by the appearance of three talking chimpanzees, who arrived mysteriously in a spacecraft. Intrigued by their intelligence, humans use them for research - until the apes attempt to escape.",
        "posterPath": "/AnbLVdUEroTfHTUVAJCxkL4R0IH.jpg",
        "backdropPath": "/7COZZS8Yfe13pEyjuF4k5WGsLEA.jpg",
        "voteAverage": 6.375,
        "releaseDate": "1971-05-20",
        "genreIds": [
            28,
            878
        ],
        "popularity": 3.1206
    },
    {
        "id": 269795,
        "title": "2:22",
        "overview": "Two planes almost collide after a blinding flash of light paralyzes air traffic controller Dylan Branson for a few seconds. Suspended from his job, Dylan starts to notice an ominous pattern of sounds and events that repeats itself in exactly the same manner every day, ending precisely at 2:22 p.m. Also drawn into a complex relationship with a woman, Dylan must figure out a way to break the power of the past and take control of time itself.",
        "posterPath": "/f88O2AkBe7KXhQznFs6zOdpClcs.jpg",
        "backdropPath": "/pA64SA1yextORgxiUqGm7KUSo2n.jpg",
        "voteAverage": 6.0,
        "releaseDate": "2017-06-29",
        "genreIds": [
            878,
            9648,
            53,
            10749
        ],
        "popularity": 1.9902
    },
    {
        "id": 28762,
        "title": "Waxwork II: Lost in Time",
        "overview": "The survivors of the first Waxwork must use a portal through time to defeat the evil that has followed them and turned their lives upside down.",
        "posterPath": "/dT2V9pZNVGOpzH17LJKg62wl3Pc.jpg",
        "backdropPath": "/3K5f069NukXn209osdL9RdRnTL.jpg",
        "voteAverage": 5.0,
        "releaseDate": "1992-05-11",
        "genreIds": [
            27,
            35,
            14
        ],
        "popularity": 0.974
    },
    {
        "id": 437,
        "title": "Cube 2: Hypercube",
        "overview": "Eight strangers awaken with no memory, in a puzzling cube-shaped room where the laws of physics do not always apply.",
        "posterPath": "/bEqqwtwUP7lm56VyeVONhv9JtYu.jpg",
        "backdropPath": "/zJqv6s4XCdHWrnoqfLqlGzzxSjH.jpg",
        "voteAverage": 5.487,
        "releaseDate": "2002-04-15",
        "genreIds": [
            53,
            878,
            9648
        ],
        "popularity": 2.2241
    },
    {
        "id": 10606,
        "title": "The Philadelphia Experiment",
        "overview": "Based on an \"actual event\" that took place in 1943. About a US Navy Destroyer Escort that disappeared from the Philadelphia Naval Shipyard, and sent two men 40 years into the future to 1984.",
        "posterPath": "/loKzciPI19uLZ6GeSYjInzdGg60.jpg",
        "backdropPath": "/4wPZaKaucs4lN7V4JWwkCN8vSwp.jpg",
        "voteAverage": 6.1,
        "releaseDate": "1984-10-05",
        "genreIds": [
            878,
            12,
            53
        ],
        "popularity": 2.1286
    },
    {
        "id": 8738,
        "title": "The Final Countdown",
        "overview": "During routine manoeuvres near Hawaii in 1980, the aircraft-carrier USS Nimitz is caught in a strange vortex-like storm, throwing the ship back in time to 1941—mere hours before the Japanese attack on Pearl Harbor.",
        "posterPath": "/nJmWPdreWnbdjMpmXB5rnJMvsK1.jpg",
        "backdropPath": "/5mO6N0SOlPQmoGYGjzOZfuX4Nmm.jpg",
        "voteAverage": 6.6,
        "releaseDate": "1980-01-31",
        "genreIds": [
            10752,
            28,
            878
        ],
        "popularity": 3.0299
    },
    {
        "id": 9339,
        "title": "Click",
        "overview": "A married workaholic, Michael Newman doesn't have time for his wife and children, not if he's to impress his ungrateful boss and earn a well-deserved promotion. So when he meets Morty, a loopy sales clerk, he gets the answer to his prayers: a magical remote that allows him to bypass life's little distractions with increasingly hysterical results.",
        "posterPath": "/oL0k5JA53PyoHSZqKb3cNkhwBCE.jpg",
        "backdropPath": "/h30q7IXCmlgR1wKLnp9LttH6BCG.jpg",
        "voteAverage": 6.302,
        "releaseDate": "2006-06-23",
        "genreIds": [
            35,
            18,
            14
        ],
        "popularity": 6.7399
    },
    {
        "id": 14069,
        "title": "The Girl Who Leapt Through Time",
        "overview": "When 17-year-old Makoto Konno gains the ability to 'leap' backwards through time, she immediately sets about improving her grades and preventing personal mishaps. However, she soon realises that changing the past isn't as simple as it seems, and eventually, will have to rely on her new powers to shape the future of herself and her friends.",
        "posterPath": "/xHnlWM8BmqY419YUccYy2KC5Jqo.jpg",
        "backdropPath": "/3c59KMNs2MYqXUb2GZe8Yfwn4kb.jpg",
        "voteAverage": 7.78,
        "releaseDate": "2006-07-15",
        "genreIds": [
            14,
            16,
            18,
            878
        ],
        "popularity": 5.5063
    },
    {
        "id": 2135,
        "title": "The Time Machine",
        "overview": "Hoping to alter the events of the past, a 19th-century inventor instead travels 800,000 years into the future, where he finds mankind divided into two warring races.",
        "posterPath": "/iYayQahkghlbAsfOQX8b5eBzGVy.jpg",
        "backdropPath": "/i0eOILDW8HipIkOUSKhB1dvZzNJ.jpg",
        "voteAverage": 6.301,
        "releaseDate": "2002-03-04",
        "genreIds": [
            878,
            12,
            28
        ],
        "popularity": 4.8836
    },
    {
        "id": 2157,
        "title": "Lost in Space",
        "overview": "The prospects for continuing life on Earth in the year 2058 are grim. So the Robinsons are launched into space to colonize Alpha Prime, the only other inhabitable planet in the galaxy. But when a stowaway sabotages the mission, the Robinsons find themselves hurtling through uncharted space.",
        "posterPath": "/fCocPDUFuKswY2GxDdfYsT9BXMd.jpg",
        "backdropPath": "/qu0HXKZBsugBiHJm4QZdFiSrvPi.jpg",
        "voteAverage": 5.4,
        "releaseDate": "1998-04-03",
        "genreIds": [
            878,
            12
        ],
        "popularity": 3.5784
    },
    {
        "id": 14337,
        "title": "Primer",
        "overview": "A group of fledgling inventors discover a complex method to manipulate reality. At first, they successfully game the stock market with it, but the consequences of the invention start to catch up with them.",
        "posterPath": "/xEoq2WmDzpzxhkHEsmOYOg6BPg6.jpg",
        "backdropPath": "/yxlGeAK6BrbKng8VSJSKTpSXSsL.jpg",
        "voteAverage": 6.762,
        "releaseDate": "2004-10-08",
        "genreIds": [
            878,
            18,
            53
        ],
        "popularity": 2.864
    },
    {
        "id": 329865,
        "title": "Arrival",
        "overview": "Taking place after alien crafts land around the world, an expert linguist is recruited by the military to determine whether they come in peace or are a threat.",
        "posterPath": "/pEzNVQfdzYDzVK0XqxERIw2x2se.jpg",
        "backdropPath": "/r8FD6CC3GgjWaGVkZh00AcedfpA.jpg",
        "voteAverage": 7.624,
        "releaseDate": "2016-11-10",
        "genreIds": [
            18,
            878,
            9648
        ],
        "popularity": 17.7263
    },
    {
        "id": 199,
        "title": "Star Trek: First Contact",
        "overview": "The Borg, a relentless race of cyborgs, are on a direct course for Earth. Violating orders to stay away from the battle, Captain Picard and the crew of the newly-commissioned USS Enterprise E pursue the Borg back in time to prevent the invaders from changing Federation history and assimilating the galaxy.",
        "posterPath": "/iqhHe893Vcf07jNkNQ31tu85dKG.jpg",
        "backdropPath": "/wygUDDRNpeKUnkekRGeLCZM93tA.jpg",
        "voteAverage": 7.3,
        "releaseDate": "1996-11-22",
        "genreIds": [
            878,
            28,
            12,
            53
        ],
        "popularity": 6.7818
    },
    {
        "id": 10122,
        "title": "Flight of the Navigator",
        "overview": "12-year-old David is accidentally knocked out in the forest near his home, but when he awakens eight years have passed. His family is overjoyed to have him back, but is just as perplexed as he is that he hasn't aged. When a NASA scientist discovers a UFO nearby, David gets the chance to unravel the mystery and recover the life he lost.",
        "posterPath": "/tdRgQWMximj0tL6OWu9kRTtePmI.jpg",
        "backdropPath": "/8esvgUVVX4GGXLGuGvKDYFNqVdt.jpg",
        "voteAverage": 7.0,
        "releaseDate": "1986-07-30",
        "genreIds": [
            10751,
            878,
            12
        ],
        "popularity": 2.8409
    },
    {
        "id": 54427,
        "title": "Stork Day",
        "overview": "Filippo is a star on the Italian TV. He works for a documentary series about wild animals and nature. He is sent to Tenerife (Spain) to shot an issue about the local stork. It is the 13th of August. After he did his job is time to leave, but the ferry couldn't operate. He has to spend the night in the island. The day after is again the 13th of August, and Filippo live again the same day for different times. Something has to change to exit the paranoid and unrealistic situation.",
        "posterPath": "/cLzoub8a2mFAMoHiXIlmms6YpRm.jpg",
        "backdropPath": "/oixwTGtaXdBo17B0Llpj84ySXdj.jpg",
        "voteAverage": 6.6,
        "releaseDate": "2004-01-16",
        "genreIds": [
            35,
            14
        ],
        "popularity": 0.6168
    },
    {
        "id": 253310,
        "title": "Premature",
        "overview": "On the most important day of his young life, a high school senior is forced to relive his failed attempt at losing his virginity over and over again, until he gets it right.",
        "posterPath": "/iU7OQ2oG2HyIqmZjikXA4N86wpN.jpg",
        "backdropPath": "/qITMDD5ggmuUsShtJT1MAusnT.jpg",
        "voteAverage": 5.473,
        "releaseDate": "2014-07-02",
        "genreIds": [
            35
        ],
        "popularity": 2.7309
    },
    {
        "id": 148948,
        "title": "The Time Machine",
        "overview": "A scientist builds a machine that will enable him to travel back and forth in time, but when he puts it in motion, he gets more than he bargained for.",
        "posterPath": "/fk6qjZuzVKS3i5Rz3YPIhoE0ERR.jpg",
        "backdropPath": "/u1RBbSLDfKKjru6EhBEJMgiuXss.jpg",
        "voteAverage": 4.7,
        "releaseDate": "1978-11-05",
        "genreIds": [
            12,
            878,
            10770
        ],
        "popularity": 1.1692
    },
    {
        "id": 24420,
        "title": "The Time Traveler's Wife",
        "overview": "Due to a genetic disorder, handsome librarian Henry DeTamble involuntarily zips through time, appearing at various moments in the life of his true love, the beautiful artist Clare Abshire.",
        "posterPath": "/J3ewuzQwhFro0pDpdcbZ4j7MYy.jpg",
        "backdropPath": "/3B4DbexR2hXINqJN6LqhmmAaVeS.jpg",
        "voteAverage": 6.936,
        "releaseDate": "2009-08-14",
        "genreIds": [
            18,
            10749,
            14
        ],
        "popularity": 3.2055
    },
    {
        "id": 7551,
        "title": "Déjà Vu",
        "overview": "Called in to recover evidence in the aftermath of a horrific explosion on a New Orleans ferry, Federal agent Doug Carlin gets pulled away from the scene and taken to a top-secret government lab that uses a time-shifting surveillance device to help prevent crime.",
        "posterPath": "/eTX6hklzFOiEVqVukNCEedZKhix.jpg",
        "backdropPath": "/mhi2fRCbEXtN43FNiq45WQg0DFe.jpg",
        "voteAverage": 6.876,
        "releaseDate": "2006-11-22",
        "genreIds": [
            28,
            53,
            878
        ],
        "popularity": 8.9189
    },
    {
        "id": 122906,
        "title": "About Time",
        "overview": "The night after another unsatisfactory New Year's party, Tim's father tells his son that the men in his family have always had the ability to travel through time. They can't change history, but they can change what happens and has happened in their own lives. Thus begins the start of a lesson in learning to appreciate life itself as it is, as it comes, and most importantly, the people living alongside us.",
        "posterPath": "/ls6zswrOZVhCXQBh96DlbnLBajM.jpg",
        "backdropPath": "/einbto9qLXFx9QXxEHylaxDbKPx.jpg",
        "voteAverage": 7.905,
        "releaseDate": "2013-09-04",
        "genreIds": [
            18,
            10749,
            14
        ],
        "popularity": 8.952
    },
    {
        "id": 14620,
        "title": "The Butterfly Effect 2",
        "overview": "After his girlfriend, Julie, and two best friends are killed in a tragic auto accident, Nick struggles to cope with his loss and grief. Suffering from migraine-like seizures, Nick soon discovers that he has the power to change the past via his memories. However, his time-traveling attempts to alter the past and save his one true love have unexpected and dire consequences.",
        "posterPath": "/g87nPhHf2xfENBV6PCbkO88sthd.jpg",
        "backdropPath": "/woUBg7Se10brZajZjg2uBklwXlM.jpg",
        "voteAverage": 5.0,
        "releaseDate": "2006-08-17",
        "genreIds": [
            18,
            878,
            53
        ],
        "popularity": 3.4204
    },
    {
        "id": 16258,
        "title": "The Butterfly Effect 3: Revelations",
        "overview": "The story revolves around a man trying to uncover the mysterious death of his girlfriend and save an innocent man from the death chamber in the process, by using his unique power to time travel. However in attempting to do this, he also frees a spiteful serial-killer.",
        "posterPath": "/7utgDyfae053YExAuUKcwkzUKMs.jpg",
        "backdropPath": "/dZ1Uk7mCn1CHmeDYnlYGo0P0b2D.jpg",
        "voteAverage": 5.5,
        "releaseDate": "2009-01-09",
        "genreIds": [
            878,
            53,
            18,
            80
        ],
        "popularity": 2.0648
    },
    {
        "id": 220289,
        "title": "Coherence",
        "overview": "Four couples gather for dinner the night a mysterious and powerful comet passes overhead.",
        "posterPath": "/ezUtb9m5DeLwL2gxi4gktzNCvQv.jpg",
        "backdropPath": "/cvGE73s935bXEAVt2W0zADPPegG.jpg",
        "voteAverage": 7.215,
        "releaseDate": "2014-04-06",
        "genreIds": [
            53,
            878
        ],
        "popularity": 4.5124
    },
    {
        "id": 9667,
        "title": "The Jacket",
        "overview": "A military veteran goes on a journey into the future, where he can foresee his death and is left with questions that could save his life and those he loves.",
        "posterPath": "/bt89UfRhjAvJDAO9CWJnRFXAN3p.jpg",
        "backdropPath": "/oMson3ThVDsgHUMbdFFyUdpLU2M.jpg",
        "voteAverage": 6.869,
        "releaseDate": "2005-03-04",
        "genreIds": [
            18,
            9648,
            878,
            53,
            14
        ],
        "popularity": 2.9635
    },
    {
        "id": 71700,
        "title": "Repeaters",
        "overview": "A gritty mind-bending thriller about three twenty-somethings who find themselves in an impossible time labyrinth, where each day they awaken to the same terrifying day as the preceding one.",
        "posterPath": "/9nQuL87o5AcUayeZM3cOXw1VbIv.jpg",
        "backdropPath": "/5HMmzpWnH6b9gV3WQ3LscPRoCJn.jpg",
        "voteAverage": 5.8,
        "releaseDate": "2011-04-22",
        "genreIds": [
            18,
            28,
            80,
            878
        ],
        "popularity": 1.5749
    },
    {
        "id": 98568,
        "title": "Enter Nowhere",
        "overview": "Three strangers arrive one by one to a mysterious cabin in the middle of nowhere after enduring separate life-altering predicaments. Searching for a way out of the woods, frustrated, hungry and battling to stay warm they discover their mysterious connection and realize what they have to do in order to get out of the woods alive.",
        "posterPath": "/eBWZmjzehYXmVTCsFan9RnzmZ7Z.jpg",
        "backdropPath": "/2OYkD6dVs45IpmpGtz9fAqFbHJ4.jpg",
        "voteAverage": 6.393,
        "releaseDate": "2015-02-02",
        "genreIds": [
            9648,
            53,
            878
        ],
        "popularity": 1.1348
    },
    {
        "id": 26466,
        "title": "Triangle",
        "overview": "When Jess sets sail on a yacht with a group of friends, she cannot shake the feeling that there is something wrong.",
        "posterPath": "/cRlMrbc4Iof7vN0ZqHwJnMBYBLi.jpg",
        "backdropPath": "/rlVpm5r7vZYyU9JHWf9UGOVDo5M.jpg",
        "voteAverage": 6.92,
        "releaseDate": "2009-10-16",
        "genreIds": [
            27
        ],
        "popularity": 4.1147
    },
    {
        "id": 14139,
        "title": "Timecrimes",
        "overview": "A man accidentally gets into a time machine and travels back in time nearly an hour. Finding himself will be the first of a series of disasters of unforeseeable consequences.",
        "posterPath": "/zdxQRP7mzczMJBwKnv8MCPRq7rQ.jpg",
        "backdropPath": "/anA2hEvG5SWrYETwcJ1SUPUfKDz.jpg",
        "voteAverage": 7.015,
        "releaseDate": "2007-11-01",
        "genreIds": [
            878,
            53
        ],
        "popularity": 2.7794
    },
    {
        "id": 257117,
        "title": "Blood Punch",
        "overview": "Milton, a college dropout, was only supposed to cook meth for one day. Broken out of rehab by a brash young woman and her trigger-happy (\"ex\") boyfriend and driven to a remote cabin the woods, Milton finds himself drawn into a dangerous love triangle gone haywire. The couple's deadpan half-truths spin around Milton like a song on repeat. They seem to read him like an open book, until a mysterious message opens his eyes to his cursed existence. With unlimited ammunition, any hunting tool they could desire, and an ever-growing body count, for what did Milton really sign up?",
        "posterPath": "/qQZkm86UV5qiRPbcWQOPN6iF6HN.jpg",
        "backdropPath": "/69kwyBRuR2S3uEttJpb6ALc0MkH.jpg",
        "voteAverage": 6.367,
        "releaseDate": "2014-02-21",
        "genreIds": [
            27,
            53
        ],
        "popularity": 0.9075
    },
    {
        "id": 459073,
        "title": "A Day",
        "overview": "Three years ago,  a father saved his daughter's life. After she's involved in a car accident, it looks like he'll have to do it again, no matter how many attempts it takes.",
        "posterPath": "/1Tgtamqk3Kp9iwflrDWRRTjGjXB.jpg",
        "backdropPath": "/bqZrVGzygjnggv5AeZkSxPKGsCs.jpg",
        "voteAverage": 7.8,
        "releaseDate": "2017-06-15",
        "genreIds": [
            9648,
            53,
            18
        ],
        "popularity": 1.9577
    },
    {
        "id": 126323,
        "title": "Mine Games",
        "overview": "A group of young friends make an incomprehensible discovery in an abandoned mine, but the more they try to change the future, the more they seal their fate.",
        "posterPath": "/4EumAjlw1pIpqoz8m0fJr1Tj2fm.jpg",
        "backdropPath": "/9SCZHbKSgcIInFO2vsWrjj5TDRz.jpg",
        "voteAverage": 5.5,
        "releaseDate": "2012-12-01",
        "genreIds": [
            53,
            27
        ],
        "popularity": 0.7922
    },
    {
        "id": 440021,
        "title": "Happy Death Day",
        "overview": "Caught in a bizarre and terrifying time warp, college student Tree finds herself repeatedly reliving the day of her murder, ultimately realizing that she must identify the killer and the reason for her death before her chances of survival run out.",
        "posterPath": "/cTaEIUYTt52ooq9quVbAQ7NpGwo.jpg",
        "backdropPath": "/9XSEL3EMC2D8k4UcYBn8etgRxPg.jpg",
        "voteAverage": 6.658,
        "releaseDate": "2017-10-12",
        "genreIds": [
            35,
            27,
            9648
        ],
        "popularity": 4.06
    },
    {
        "id": 24559,
        "title": "Slaughterhouse-Five",
        "overview": "Billy Pilgrim, a veteran of the Second World War, finds himself mysteriously detached from time, so that he is able to travel, without being able to help it, from the days of his childhood to those of his peculiar life on a distant planet called Tralfamadore, passing through his bitter experience as a prisoner of war in the German city of Dresden, over which looms the inevitable shadow of an unspeakable tragedy.",
        "posterPath": "/gM2q9pGW9x2zdEMPRsXLBgTDDFH.jpg",
        "backdropPath": "/tIlhG6ZmJFF1NKEA3aMWJhXhW78.jpg",
        "voteAverage": 6.5,
        "releaseDate": "1972-03-15",
        "genreIds": [
            18,
            878,
            10752
        ],
        "popularity": 1.7592
    },
    {
        "id": 449078,
        "title": "Time Sweep",
        "overview": "Still reeling from the loss of his wife, a grieving man goes to great lengths to see her again. But their reunion comes at a stunning cost.",
        "posterPath": "/iibtfg6qHD9mY0vilgsFTrtQW0S.jpg",
        "backdropPath": "/8jo6dz2rsqMKyb21XydRa5AMHEl.jpg",
        "voteAverage": 4.7,
        "releaseDate": "2016-05-12",
        "genreIds": [
            18,
            53
        ],
        "popularity": 0.102
    },
    {
        "id": 352481,
        "title": "Stealing Time",
        "overview": "When a down-on-his-luck inventor builds a time machine to change the past, he unwittingly sets off a disastrous chain of events.",
        "posterPath": "/dctevSC0jlERr1aVElStGUveBuX.jpg",
        "backdropPath": "/lL6kEbiyhZexpeYPKXArIjPkdEW.jpg",
        "voteAverage": 6.6,
        "releaseDate": "2015-04-25",
        "genreIds": [
            878,
            35
        ],
        "popularity": 1.096
    },
    {
        "id": 529216,
        "title": "Mirage",
        "overview": "During a mysterious thunderstorm, Vera, a young mother, manages to save a life in danger, but her good deed causes a disturbing chain of unexpected consequences.",
        "posterPath": "/hmhYM1CNBhpWTYjUEZ4leQDmIYw.jpg",
        "backdropPath": "/jOGRt1JEzfgmXbC88vGv4DwDppj.jpg",
        "voteAverage": 7.448,
        "releaseDate": "2018-11-30",
        "genreIds": [
            53,
            18,
            9648,
            14
        ],
        "popularity": 4.0279
    },
    {
        "id": 582607,
        "title": "See You Yesterday",
        "overview": "As two teen prodigies try to master the art of time travel, a tragic police shooting sends them on a series of dangerous trips to the past.",
        "posterPath": "/d5uA1DdiWK5KH5yzyMfh1X3uXie.jpg",
        "backdropPath": "/zVL1yX2jIjuAVqZFzyEhWGeD95O.jpg",
        "voteAverage": 5.546,
        "releaseDate": "2019-05-03",
        "genreIds": [
            878,
            18,
            12,
            80,
            28
        ],
        "popularity": 1.147
    },
    {
        "id": 299534,
        "title": "Avengers: Endgame",
        "overview": "After the devastating events of Avengers: Infinity War, the universe is in ruins due to the efforts of the Mad Titan, Thanos. With the help of remaining allies, the Avengers must assemble once more in order to undo Thanos' actions and restore order to the universe once and for all, no matter what consequences may be in store.",
        "posterPath": "/ulzhLuWrPK07P1YkdWQLZnQh1JL.jpg",
        "backdropPath": "/7RyHsO4yDXtBv1zUU3mTpHeQ0d5.jpg",
        "voteAverage": 8.234,
        "releaseDate": "2019-04-24",
        "genreIds": [
            12,
            878,
            28
        ],
        "popularity": 30.4376
    },
    {
        "id": 540970,
        "title": "Collider",
        "overview": "In the year 2033, a young girl trapped in a mysterious orphanage recklessly travels back in time to find her parents and amend her past.",
        "posterPath": "/4VMHLhqxwtx3zbE7CmQE5mhUTAq.jpg",
        "backdropPath": "/o99i9Mkb7EWLjFdyxQ91i8mIAOn.jpg",
        "voteAverage": 3.9,
        "releaseDate": "2018-08-07",
        "genreIds": [
            878
        ],
        "popularity": 0.835
    },
    {
        "id": 530382,
        "title": "In the Shadow of the Moon",
        "overview": "In 1988, Philadelphia police officer Thomas \"Locke\" Lockhart, hungry to become a detective, begins tracking a serial killer whose crimes defy scientific explanation. When the killer mysteriously resurfaces nine years later, Locke's obsession with finding the truth threatens to destroy his career, his family, and possibly his sanity.",
        "posterPath": "/5DSVYlKwEzGBxTkS95L73c3oxLs.jpg",
        "backdropPath": "/eZKJ6Ez3DhVamz1CG1zwUpdwaAS.jpg",
        "voteAverage": 6.2,
        "releaseDate": "2019-09-27",
        "genreIds": [
            878,
            53
        ],
        "popularity": 2.8253
    },
    {
        "id": 455839,
        "title": "Time Trap",
        "overview": "A group of students become trapped inside a mysterious cave where they discover time passes differently underground than on the surface.",
        "posterPath": "/583rpyMn8UL8F2oH26Sz6WoKDDe.jpg",
        "backdropPath": "/lRFtFFIoGQfHxyHNS254Ew7PV9c.jpg",
        "voteAverage": 6.304,
        "releaseDate": "2018-06-22",
        "genreIds": [
            878,
            12
        ],
        "popularity": 3.7914
    },
    {
        "id": 10559,
        "title": "Frequency",
        "overview": "When a rare phenomenon gives police officer John Sullivan the chance to speak to his father, 30 years in the past, he takes the opportunity to prevent his dad's tragic death.  After his actions inadvertently give rise to a series of brutal murders he and his father must find a way to fix the consequences of altering time.",
        "posterPath": "/eu3Hrjj271dnBdNAF0HqfmwWASt.jpg",
        "backdropPath": "/pBS51YVR78U2E6s2YXdIh8hPGSn.jpg",
        "voteAverage": 7.263,
        "releaseDate": "2000-04-28",
        "genreIds": [
            878,
            53,
            10751,
            80
        ],
        "popularity": 4.803
    },
    {
        "id": 7249,
        "title": "Futurama: Bender's Big Score",
        "overview": "The Planet Express crew return from cancellation, only to be robbed blind by hideous \"sprunging\" scam artists.  Things go from bad to worse when the scammers hack Bender, start traveling through time, and take Earth over entirely!  Will the crew be able to save the day, or will Bender's larcenous tendencies and their general incompetence doom them all?",
        "posterPath": "/bmVE90IHvx4uXQgtbRtu4RyMWpt.jpg",
        "backdropPath": "/txzQ45okJz2fLUQTClCr2Vuk9Nt.jpg",
        "voteAverage": 7.383,
        "releaseDate": "2007-11-27",
        "genreIds": [
            16,
            35,
            878
        ],
        "popularity": 1.9337
    },
    {
        "id": 45612,
        "title": "Source Code",
        "overview": "When decorated soldier Captain Colter Stevens wakes up in the body of an unknown man, he discovers he's part of a mission to find the bomber of a Chicago commuter train.",
        "posterPath": "/nTr0lvAzeQmUjgSgDEHTJpnrxTz.jpg",
        "backdropPath": "/s2Cu1y9Al9RbwRU5blAH8wMCrBI.jpg",
        "voteAverage": 7.308,
        "releaseDate": "2011-03-30",
        "genreIds": [
            53,
            878,
            9648
        ],
        "popularity": 7.5637
    },
    {
        "id": 24750,
        "title": "Time After Time",
        "overview": "Writer H. G. Wells pursues Jack the Ripper to modern day San Francisco after the infamous serial killer steals his time machine to escape the 19th century.",
        "posterPath": "/A4SXZxQempzTUReRlQiFaYc6KaC.jpg",
        "backdropPath": "/1HDpR7nLqQcGSdbC41pSxCPjjyH.jpg",
        "voteAverage": 6.8,
        "releaseDate": "1979-09-28",
        "genreIds": [
            12,
            18,
            35,
            878,
            53
        ],
        "popularity": 2.8616
    },
    {
        "id": 577922,
        "title": "Tenet",
        "overview": "Armed with only one word - Tenet - and fighting for the survival of the entire world, the Protagonist journeys through a twilight world of international espionage on a mission that will unfold in something beyond real time.",
        "posterPath": "/aCIFMriQh8rvhxpN1IWGgvH0Tlg.jpg",
        "backdropPath": "/7BYtnXUfweV6EryNYDpZFeS31Ia.jpg",
        "voteAverage": 7.174,
        "releaseDate": "2020-08-22",
        "genreIds": [
            28,
            53,
            878
        ],
        "popularity": 9.9147
    },
    {
        "id": 451925,
        "title": "Time Freak",
        "overview": "Stillman, a heartbroken physics student, builds a time machine when his girlfriend breaks up with him. Going back in time, he attempts to save their relationship by fixing every mistake he made—while dragging his best friend along in the process.",
        "posterPath": "/oSDctngY0Oiq6l2LcJDk8k6smvg.jpg",
        "backdropPath": "/il036klfxddKrHHZPpxvWc0L5Kr.jpg",
        "voteAverage": 6.7,
        "releaseDate": "2018-11-09",
        "genreIds": [
            878,
            35,
            10749
        ],
        "popularity": 2.2834
    },
    {
        "id": 528085,
        "title": "2067",
        "overview": "A lowly utility worker is called to the future by a mysterious radio signal, he must leave his dying wife to embark on a journey that will force him to face his deepest fears in an attempt to change the fabric of reality and save humankind from its greatest environmental crisis yet.",
        "posterPath": "/7D430eqZj8y3oVkLFfsWXGRcpEG.jpg",
        "backdropPath": "/5UkzNSOK561c2QRy2Zr4AkADzLT.jpg",
        "voteAverage": 5.4,
        "releaseDate": "2020-10-01",
        "genreIds": [
            878
        ],
        "popularity": 2.4066
    },
    {
        "id": 346385,
        "title": "The History of Time Travel",
        "overview": "A fictional documentary about the creation of the world's first time machine, the men who created it, and the unintended ramifications it has on world events.",
        "posterPath": "/q1C0qZZ59j2Tsejd0SlFt5GPKIe.jpg",
        "backdropPath": "/bVHxZZxe5XIvBebuHMzIrJeBenO.jpg",
        "voteAverage": 6.3,
        "releaseDate": "2014-10-25",
        "genreIds": [
            878,
            18
        ],
        "popularity": 0.3979
    },
    {
        "id": 391199,
        "title": "Displacement",
        "overview": "A young physics student must find a way to reverse a deadly quantum time anomaly and solve the murder of her boyfriend while battling short-term memory loss and time slips caused by the event.",
        "posterPath": "/iczxJ9Us0rMtYbkPloHw9c3Zqji.jpg",
        "backdropPath": "/9LUJeECs840bpuf69MG5Tlv3ZUD.jpg",
        "voteAverage": 5.0,
        "releaseDate": "2016-06-15",
        "genreIds": [
            53,
            878,
            10770
        ],
        "popularity": 0.7126
    },
    {
        "id": 383498,
        "title": "Deadpool 2",
        "overview": "Wisecracking mercenary Deadpool battles the evil and powerful Cable and other bad guys to save a boy's life.",
        "posterPath": "/to0spRl1CMDvyUbOnbb4fTk3VAd.jpg",
        "backdropPath": "/3P52oz9HPQWxcwHOwxtyrVV1LKi.jpg",
        "voteAverage": 7.489,
        "releaseDate": "2018-05-15",
        "genreIds": [
            28,
            35,
            12
        ],
        "popularity": 15.375
    },
    {
        "id": 588228,
        "title": "The Tomorrow War",
        "overview": "The world is stunned when a group of time travelers arrive from the year 2051 to deliver an urgent message: Thirty years in the future, mankind is losing a global war against a deadly alien species. The only hope for survival is for soldiers and civilians from the present to be transported to the future and join the fight. Among those recruited is high school teacher and family man Dan Forester. Determined to save the world for his young daughter, Dan teams up with a brilliant scientist and his estranged father in a desperate quest to rewrite the fate of the planet.",
        "posterPath": "/34nDCQZwaEvsy4CFO5hkGRFDCVU.jpg",
        "backdropPath": "/yizL4cEKsVvl17Wc1mGEIrQtM2F.jpg",
        "voteAverage": 7.47,
        "releaseDate": "2021-09-03",
        "genreIds": [
            28,
            878,
            12
        ],
        "popularity": 10.1018
    },
    {
        "id": 86812,
        "title": "Sound of My Voice",
        "overview": "A journalist and his girlfriend get pulled in while they investigate a cult whose leader claims to be from the future.",
        "posterPath": "/6wStc532wuBrW2NZM3TicEWDmaL.jpg",
        "backdropPath": "/xEm9JBfXdQyVvJ2FEEpzZIICZBc.jpg",
        "voteAverage": 6.3,
        "releaseDate": "2011-01-22",
        "genreIds": [
            878,
            18,
            9648,
            53
        ],
        "popularity": 1.8155
    },
    {
        "id": 84332,
        "title": "Safety Not Guaranteed",
        "overview": "Three magazine employees head out on an assignment to interview a guy who placed a classified ad seeking a companion for time travel.",
        "posterPath": "/gH0l9kiaK1Ulalbq07nqR7jtin5.jpg",
        "backdropPath": "/hOVZHM2ZEaWdytcptRhfzk0fJBv.jpg",
        "voteAverage": 6.779,
        "releaseDate": "2012-06-08",
        "genreIds": [
            35,
            10749,
            878
        ],
        "popularity": 1.937
    },
    {
        "id": 837921,
        "title": "10 Minute Time Machine",
        "overview": "The discovery of a time machine sets up the possibility of an unforgettable adventure for George and Lori...ten minutes at a time.",
        "posterPath": "/x0aPH5gPhhKqLLXjulf0qLcTDtG.jpg",
        "backdropPath": "/pwNNv7weD5qMc6piPQJfDFvhrY.jpg",
        "voteAverage": 5.5,
        "releaseDate": "2017-09-19",
        "genreIds": [
            878,
            35
        ],
        "popularity": 0.4718
    },
    {
        "id": 696806,
        "title": "The Adam Project",
        "overview": "After accidentally crash-landing in 2022, time-traveling fighter pilot Adam Reed teams up with his 12-year-old self on a mission to save the future.",
        "posterPath": "/wFjboE0aFZNbVOF05fzrka9Fqyx.jpg",
        "backdropPath": "/ewUqXnwiRLhgmGhuksOdLgh49Ch.jpg",
        "voteAverage": 6.993,
        "releaseDate": "2022-03-11",
        "genreIds": [
            12,
            878,
            35
        ],
        "popularity": 7.0326
    },
    {
        "id": 433310,
        "title": "When We First Met",
        "overview": "Using a magical photo booth that sends him back in time, Noah relives the night he met Avery over and over, trying to persuade her to fall for him.",
        "posterPath": "/pscQKoikkSJxAu8O5LKtjgGJEt1.jpg",
        "backdropPath": "/kZwpxqIXPqNfRigrqF5rN8L54a.jpg",
        "voteAverage": 6.559,
        "releaseDate": "2018-02-08",
        "genreIds": [
            35,
            10749,
            14
        ],
        "popularity": 2.5617
    },
    {
        "id": 501979,
        "title": "Bill & Ted Face the Music",
        "overview": "Yet to fulfill their rock and roll destiny, the stakes are higher than ever for the now middle-aged Bill and Ted who set out on a new adventure when a visitor from the future warns them that only their song can save life as we know it.",
        "posterPath": "/4V2nTPfeB59TcqJcUfQ9ziTi7VN.jpg",
        "backdropPath": "/ceVaixg5VUfx8j0N81FT0hRayRm.jpg",
        "voteAverage": 5.906,
        "releaseDate": "2020-08-27",
        "genreIds": [
            35,
            878,
            12,
            10402
        ],
        "popularity": 2.7676
    },
    {
        "id": 1191885,
        "title": "Flashback",
        "overview": "After a violent attack at her home, a yoga instructor sees flashbacks of her life and begins a frantic race through her past to try to save her boyfriend.",
        "posterPath": "/wQ2jQbygvJW5HsEyaCNv2WxtAnl.jpg",
        "backdropPath": "/53wwZpiHEXmqWAMGW2v5b8I2cVc.jpg",
        "voteAverage": 4.7,
        "releaseDate": "2023-10-20",
        "genreIds": [
            14,
            10749,
            53
        ],
        "popularity": 0.9509
    },
    {
        "id": 1032394,
        "title": "Stalled",
        "overview": "Late for the most important meeting of his life, a toxic executive finds himself trapped in a time paradox within a public restroom.",
        "posterPath": "/9NRpxQRZrmKLQL9F9d0ADRB6Yx8.jpg",
        "backdropPath": "/8jgutB1N2Q6wwyFlSg83wHosPJB.jpg",
        "voteAverage": 7.6,
        "releaseDate": "2022-11-11",
        "genreIds": [
            878,
            53
        ],
        "popularity": 0.5846
    },
    {
        "id": 290859,
        "title": "Terminator: Dark Fate",
        "overview": "Decades after Sarah Connor prevented Judgment Day, a lethal new Terminator is sent to eliminate the future leader of the resistance. In a fight to save mankind, battle-hardened Sarah Connor teams up with an unexpected ally and an enhanced super soldier to stop the deadliest Terminator yet.",
        "posterPath": "/vqzNJRH4YyquRiWxCCOH0aXggHI.jpg",
        "backdropPath": "/riTANvQ8GKmQbgtC1ps3OfkU43A.jpg",
        "voteAverage": 6.414,
        "releaseDate": "2019-10-23",
        "genreIds": [
            878,
            28,
            12,
            53
        ],
        "popularity": 9.9515
    },
    {
        "id": 1426680,
        "title": "Our Times",
        "overview": "Husband and wife Nora and Héctor's scientific breakthrough lets them time travel from 1966 to 2025. As Héctor struggles, Nora thrives—but at what cost?",
        "posterPath": "/iJWSUAMJI9mRSzVBJXVUg7iIoJM.jpg",
        "backdropPath": "/dD14o9KJDbmuJ80z4vKdVnQ0zks.jpg",
        "voteAverage": 6.6,
        "releaseDate": "2025-06-09",
        "genreIds": [
            878,
            10749,
            35
        ],
        "popularity": 1.0908
    },
    {
        "id": 827931,
        "title": "Time Cut",
        "overview": "A teen in 2024 accidentally time-travels to 2003, days before a masked killer murders her sister. Can she change the past without destroying the future?",
        "posterPath": "/gzMFMmpJHOmOFKsAhSDac62Dyg2.jpg",
        "backdropPath": "/qYvOcinXcnebhmCxYeivurh91T1.jpg",
        "voteAverage": 5.7,
        "releaseDate": "2024-10-29",
        "genreIds": [
            27,
            878,
            53
        ],
        "popularity": 3.2931
    },
    {
        "id": 1493253,
        "title": "The Lord of All Future Space & Time",
        "overview": "With the help of a duffle bag from the future, a grief-stricken cowboy avenges the death of his wife.",
        "posterPath": "/s7bSoWmxma89SQKUnJBVsdTDYgf.jpg",
        "backdropPath": "/8iS6AtYRjJPkdg6eEUmeN4v6RD5.jpg",
        "voteAverage": 6.5,
        "releaseDate": "2025-06-18",
        "genreIds": [
            12,
            35,
            878,
            37
        ],
        "popularity": 0.5257
    }
]